llama_index/py.typed
llama_index/vector_stores/weaviate/__init__.py
llama_index/vector_stores/weaviate/_exceptions.py
llama_index/vector_stores/weaviate/base.py
llama_index/vector_stores/weaviate/utils.py
llama_index_vector_stores_weaviate-1.4.0.dist-info/METADATA
llama_index_vector_stores_weaviate-1.4.0.dist-info/WHEEL
llama_index_vector_stores_weaviate-1.4.0.dist-info/licenses/LICENSE
llama_index_vector_stores_weaviate-1.4.0.dist-info/RECORD
